groundwork/__init__.py
groundwork/contrib/airtable/datasources.py
groundwork/core/cache.py
groundwork/core/cron.py
groundwork/core/datasources.py
groundwork/core/internal/asset_loader.py
groundwork/core/internal/class_util.py
groundwork/core/internal/collection_util.py
groundwork/core/internal/sync_manager.py
groundwork/core/management/commands/run_cron_tasks.py
groundwork/core/static/assets/main-legacy.d84db568.js
groundwork/core/static/assets/main.a39ffbad.js
groundwork/core/static/assets/map-controller-legacy.c416ec87.js
groundwork/core/static/assets/map-controller.9c6921a6.js
groundwork/core/static/assets/map-controller.dda420b9.css
groundwork/core/static/assets/map-layer-controller-legacy.e18a0a84.js
groundwork/core/static/assets/map-layer-controller.ceb4fa75.js
groundwork/core/static/assets/map-source-controller-legacy.cbc01fc9.js
groundwork/core/static/assets/map-source-controller.7418fbb5.js
groundwork/core/static/assets/map-utils-legacy.14d316bf.js
groundwork/core/static/assets/map-utils.29a36188.js
groundwork/core/static/assets/polyfills-legacy.e02ff3bf.js
groundwork/core/static/assets/stimulus-utils-legacy.1e2c92a4.js
groundwork/core/static/assets/stimulus-utils.0a5b2692.js
groundwork/core/static/assets/vendor-legacy.a2df6578.js
groundwork/core/static/assets/vendor.0af78d00.js
groundwork/core/static/manifest.json
groundwork/core/template.py
groundwork/core/templatetags/groundwork_core.py
groundwork/core/types.py
groundwork/geo/docs/map.components.md
groundwork/geo/examples.py
groundwork/geo/templates/groundwork/geo/components/map.html
groundwork/geo/templates/groundwork/geo/components/map_canvas.html
groundwork/geo/templates/groundwork/geo/components/map_config.html
groundwork/geo/templates/groundwork/geo/examples/complex_map_example.html
groundwork/geo/templates/groundwork/geo/examples/map_example.html
groundwork/geo/templatetags/groundwork_geo.py
groundwork/geo/territories/uk/internal/serializers.py
groundwork/geo/territories/uk/ons.py
groundwork_django-0.2.0.dist-info/LICENSE
groundwork_django-0.2.0.dist-info/WHEEL
groundwork_django-0.2.0.dist-info/METADATA
groundwork_django-0.2.0.dist-info/RECORD
